ecl/__init__.py
ecl/connection.py
ecl/exceptions.py
ecl/format.py
ecl/module_loader.py
ecl/profile.py
ecl/proxy.py
ecl/proxy2.py
ecl/resource.py
ecl/resource2.py
ecl/service_filter.py
ecl/session.py
ecl/utils.py
ecl/version.py
ecl/baremetal/__init__.py
ecl/baremetal/baremetal_service.py
ecl/baremetal/exceptions.py
ecl/baremetal/version.py
ecl/baremetal/v2/__init__.py
ecl/baremetal/v2/_proxy.py
ecl/baremetal/v2/availability_zone.py
ecl/baremetal/v2/chassis.py
ecl/baremetal/v2/flavor.py
ecl/baremetal/v2/keypair.py
ecl/baremetal/v2/limits.py
ecl/baremetal/v2/metadata.py
ecl/baremetal/v2/nic_physical_port.py
ecl/baremetal/v2/server.py
ecl/baremetal/v2/stock.py
ecl/baremetal/v2/uefi.py
ecl/block_store/__init__.py
ecl/block_store/block_store_service.py
ecl/block_store/v2/__init__.py
ecl/block_store/v2/_proxy.py
ecl/block_store/v2/availability_zone.py
ecl/block_store/v2/extension.py
ecl/block_store/v2/limit.py
ecl/block_store/v2/metadata.py
ecl/block_store/v2/quota.py
ecl/block_store/v2/type.py
ecl/block_store/v2/volume.py
ecl/compute/__init__.py
ecl/compute/compute_service.py
ecl/compute/version.py
ecl/compute/v2/__init__.py
ecl/compute/v2/_proxy.py
ecl/compute/v2/availability_zone.py
ecl/compute/v2/extension.py
ecl/compute/v2/flavor.py
ecl/compute/v2/image.py
ecl/compute/v2/keypair.py
ecl/compute/v2/limits.py
ecl/compute/v2/metadata.py
ecl/compute/v2/quota.py
ecl/compute/v2/server.py
ecl/compute/v2/server_action.py
ecl/compute/v2/server_interface.py
ecl/compute/v2/server_volume.py
ecl/compute/v2/volume.py
ecl/connectivity/__init__.py
ecl/connectivity/connectivity_service.py
ecl/connectivity/exceptions.py
ecl/connectivity/version.py
ecl/connectivity/v1/__init__.py
ecl/connectivity/v1/_proxy.py
ecl/connectivity/v1/cic.py
ecl/connectivity/v1/mcic.py
ecl/connectivity/v1/operation.py
ecl/connectivity/v1/server_segment.py
ecl/dedicated_hypervisor/__init__.py
ecl/dedicated_hypervisor/dedicated_hypervisor_service.py
ecl/dedicated_hypervisor/exceptions.py
eclsdk-1.8.0.dist-info/AUTHORS
eclsdk-1.8.0.dist-info/LICENSE
eclsdk-1.8.0.dist-info/METADATA
eclsdk-1.8.0.dist-info/PKG-INFO_sv
eclsdk-1.8.0.dist-info/WHEEL
eclsdk-1.8.0.dist-info/pbr.json
eclsdk-1.8.0.dist-info/top_level.txt
eclsdk-1.8.0.dist-info/RECORD
