Metadata-Version: 2.1
Name: eclsdk
Version: 1.8.0
Summary: SDK for building applications to work with Enterprise Cloud 2.0
Home-page: https://ecl.ntt.com
Author: NTT DOCOMO BUSINESS
License: Apache License, Version 2.0
Platform: UNKNOWN
Classifier: Intended Audience :: Information Technology
Classifier: Intended Audience :: System Administrators
Classifier: License :: OSI Approved :: Apache Software License
Classifier: Operating System :: POSIX :: Linux
Classifier: Programming Language :: Python
Classifier: Programming Language :: Python :: 2
Classifier: Programming Language :: Python :: 2.7
Classifier: Programming Language :: Python :: 3
Classifier: Programming Language :: Python :: 3.3
Classifier: Programming Language :: Python :: 3.4
Classifier: Programming Language :: Python :: 3.7
License-File: LICENSE
License-File: AUTHORS
Requires-Dist: pbr>=1.6
Requires-Dist: six>=1.9.0
Requires-Dist: stevedore>=1.16.0
Requires-Dist: os-client-config!=1.19.0,>=1.13.1
Requires-Dist: keystoneauth1<=3.4.0,>=2.10.0
Requires-Dist: openstacksdk<=0.13.0
